telos/__init__.py
telos-0.0.1.dev0.dist-info/WHEEL
telos-0.0.1.dev0.dist-info/METADATA
telos-0.0.1.dev0.dist-info/RECORD
