Metadata-Version: 2.1
Name: telos
Version: 0.0.1.dev0
Summary: This is telos. 
Author-email: Joerg Schneider <schneider.joerg@bcg.com>
